nxswriter/ClientSource.py
nxswriter/DBaseSource.py
nxswriter/DataHolder.py
nxswriter/DataSourceFactory.py
nxswriter/DataSourcePool.py
nxswriter/DataSources.py
nxswriter/DecoderPool.py
nxswriter/EAttribute.py
nxswriter/EField.py
nxswriter/EGroup.py
nxswriter/ELink.py
nxswriter/EStrategy.py
nxswriter/EVirtualField.py
nxswriter/Element.py
nxswriter/ElementThread.py
nxswriter/Errors.py
nxswriter/FElement.py
nxswriter/FetchNameHandler.py
nxswriter/H5Elements.py
nxswriter/InnerXMLParser.py
nxswriter/Metadata.py
nxswriter/NXSFromXML.py
nxswriter/NXSWriter.py
nxswriter/NexusXMLHandler.py
nxswriter/PyEvalSource.py
nxswriter/Release.py
nxswriter/StreamSet.py
nxswriter/TangoDataWriter.py
nxswriter/TangoSource.py
nxswriter/ThreadPool.py
nxswriter/Types.py
nxswriter/__init__.py
nxswriter-3.18.1.data/scripts/NXSDataWriter
nxswriter-3.18.1.data/scripts/nxsfromxml
nxswriter-3.18.1.dist-info/METADATA
nxswriter-3.18.1.dist-info/WHEEL
nxswriter-3.18.1.dist-info/top_level.txt
nxswriter-3.18.1.dist-info/RECORD
