Metadata-Version: 2.1
Name: nxswriter
Version: 3.18.1
Summary: Nexus Data writer implemented as a Tango Server
Home-page: https://github.com/nexdatas/nxsdatawriter
Author: Jan Kotanski, Eugen Wintersberger , Halil Pasic
Author-email: jankotan@gmail.com, eugen.wintersberger@gmail.com, halil.pasic@gmail.com
License: GNU GENERAL PUBLIC LICENSE v3
Keywords: writer Tango server nexus data
Classifier: Development Status :: 5 - Production/Stable
Classifier: Intended Audience :: Science/Research
Classifier: Topic :: Scientific/Engineering :: Physics
Classifier: Topic :: Software Development :: Libraries :: Python Modules
Classifier: License :: OSI Approved :: GNU General Public License v3 (GPLv3)
Classifier: Programming Language :: Python :: 2.7
Classifier: Programming Language :: Python :: 3
Classifier: Programming Language :: Python :: 3.4
Classifier: Programming Language :: Python :: 3.5
Classifier: Programming Language :: Python :: 3.6
Classifier: Programming Language :: Python :: 3.7
Classifier: Programming Language :: Python :: 3.8
Classifier: Programming Language :: Python :: 3.9
Classifier: Programming Language :: Python :: 3.10
Classifier: Programming Language :: Python :: 3.11
Classifier: Programming Language :: Python :: 3.12
Classifier: Programming Language :: Python :: 3.13
Requires-Dist: lxml
Requires-Dist: numpy (>1.6.0)
Requires-Dist: nxstools (>=4.28.1)
Requires-Dist: pytz
